{
  "last_run": "2026-01-02T17:20:33.637969+00:00",
  "tracked_departures": [
    {
      "key": "925_966635_50195",
      "route_id": "925",
      "trip_id": "966635",
      "stop_id": "50195",
      "original_departure_time": "2026-01-02T15:26:57+00:00",
      "current_departure_time": "2026-01-02T15:26:57+00:00",
      "initial_alert_sent": true,
      "initial_alert_time": "2026-01-02T15:13:28.250531+00:00",
      "delay_update_sent": false
    },
    {
      "key": "17_1012514_50195",
      "route_id": "17",
      "trip_id": "1012514",
      "stop_id": "50195",
      "original_departure_time": "2026-01-02T15:48:34+00:00",
      "current_departure_time": "2026-01-02T15:48:34+00:00",
      "initial_alert_sent": true,
      "initial_alert_time": "2026-01-02T15:38:28.774565+00:00",
      "delay_update_sent": false
    },
    {
      "key": "925_972950_50195",
      "route_id": "925",
      "trip_id": "972950",
      "stop_id": "50195",
      "original_departure_time": "2026-01-02T15:50:27+00:00",
      "current_departure_time": "2026-01-02T15:50:27+00:00",
      "initial_alert_sent": true,
      "initial_alert_time": "2026-01-02T15:38:28.774565+00:00",
      "delay_update_sent": false
    },
    {
      "key": "17_1012482_50195",
      "route_id": "17",
      "trip_id": "1012482",
      "stop_id": "50195",
      "original_departure_time": "2026-01-02T16:01:09+00:00",
      "current_departure_time": "2026-01-02T16:01:09+00:00",
      "initial_alert_sent": true,
      "initial_alert_time": "2026-01-02T15:53:58.314431+00:00",
      "delay_update_sent": false
    },
    {
      "key": "925_970400_50195",
      "route_id": "925",
      "trip_id": "970400",
      "stop_id": "50195",
      "original_departure_time": "2026-01-02T16:05:24+00:00",
      "current_departure_time": "2026-01-02T16:05:24+00:00",
      "initial_alert_sent": true,
      "initial_alert_time": "2026-01-02T15:53:58.314431+00:00",
      "delay_update_sent": false
    },
    {
      "key": "17_1085614_50195",
      "route_id": "17",
      "trip_id": "1085614",
      "stop_id": "50195",
      "original_departure_time": "2026-01-02T16:47:08+00:00",
      "current_departure_time": "2026-01-02T16:47:08+00:00",
      "initial_alert_sent": true,
      "initial_alert_time": "2026-01-02T16:30:48.887032+00:00",
      "delay_update_sent": false
    },
    {
      "key": "925_973778_50195",
      "route_id": "925",
      "trip_id": "973778",
      "stop_id": "50195",
      "original_departure_time": "2026-01-02T16:39:31+00:00",
      "current_departure_time": "2026-01-02T16:39:31+00:00",
      "initial_alert_sent": true,
      "initial_alert_time": "2026-01-02T16:30:48.887032+00:00",
      "delay_update_sent": false
    },
    {
      "key": "17_1012009_50195",
      "route_id": "17",
      "trip_id": "1012009",
      "stop_id": "50195",
      "original_departure_time": "2026-01-02T17:00:39+00:00",
      "current_departure_time": "2026-01-02T17:00:39+00:00",
      "initial_alert_sent": true,
      "initial_alert_time": "2026-01-02T16:53:40.821368+00:00",
      "delay_update_sent": false
    },
    {
      "key": "925_973798_50195",
      "route_id": "925",
      "trip_id": "973798",
      "stop_id": "50195",
      "original_departure_time": "2026-01-02T17:01:39+00:00",
      "current_departure_time": "2026-01-02T17:01:39+00:00",
      "initial_alert_sent": true,
      "initial_alert_time": "2026-01-02T16:53:40.821368+00:00",
      "delay_update_sent": false
    },
    {
      "key": "925_967121_50195",
      "route_id": "925",
      "trip_id": "967121",
      "stop_id": "50195",
      "original_departure_time": "2026-01-02T17:08:37+00:00",
      "current_departure_time": "2026-01-02T17:08:37+00:00",
      "initial_alert_sent": true,
      "initial_alert_time": "2026-01-02T16:53:40.821368+00:00",
      "delay_update_sent": false
    },
    {
      "key": "17_1010215_50195",
      "route_id": "17",
      "trip_id": "1010215",
      "stop_id": "50195",
      "original_departure_time": "2026-01-02T17:30:53+00:00",
      "current_departure_time": "2026-01-02T17:30:53+00:00",
      "initial_alert_sent": true,
      "initial_alert_time": "2026-01-02T17:20:33.637969+00:00",
      "delay_update_sent": false
    },
    {
      "key": "925_972615_50195",
      "route_id": "925",
      "trip_id": "972615",
      "stop_id": "50195",
      "original_departure_time": "2026-01-02T17:29:54+00:00",
      "current_departure_time": "2026-01-02T17:29:54+00:00",
      "initial_alert_sent": true,
      "initial_alert_time": "2026-01-02T17:20:33.637969+00:00",
      "delay_update_sent": false
    }
  ]
}